conxa/__init__.py
conxa/client.py
conxa/exceptions.py
conxa/models.py
conxa/qr.py
conxa_sdk-1.3.4.dist-info/licenses/LICENSE
conxa_sdk-1.3.4.dist-info/METADATA
conxa_sdk-1.3.4.dist-info/WHEEL
conxa_sdk-1.3.4.dist-info/top_level.txt
conxa_sdk-1.3.4.dist-info/RECORD
