Metadata-Version: 2.4
Name: conxa-sdk
Version: 1.3.4
Summary: Python SDK for integrating CONXA Wallet payments into AI services
Home-page: https://github.com/conxa/python-sdk
Author: CONXA Team
Author-email: support@conxa.in
Project-URL: Documentation, https://docs.conxa.in
Project-URL: Bug Reports, https://github.com/conxa/python-sdk/issues
Project-URL: Source, https://github.com/conxa/python-sdk
Keywords: conxa,wallet,payments,ai,tokens,sdk,api
Classifier: Development Status :: 5 - Production/Stable
Classifier: Intended Audience :: Developers
Classifier: License :: OSI Approved :: MIT License
Classifier: Operating System :: OS Independent
Classifier: Programming Language :: Python :: 3
Classifier: Programming Language :: Python :: 3.9
Classifier: Programming Language :: Python :: 3.10
Classifier: Programming Language :: Python :: 3.11
Classifier: Programming Language :: Python :: 3.12
Classifier: Programming Language :: Python :: 3.13
Classifier: Topic :: Software Development :: Libraries :: Python Modules
Classifier: Topic :: Internet :: WWW/HTTP
Requires-Python: >=3.9
License-File: LICENSE
Requires-Dist: requests>=2.32.0
Requires-Dist: qrcode[pil]>=8.0.0
Requires-Dist: Pillow>=10.0.0
Provides-Extra: dev
Requires-Dist: pytest>=7.0.0; extra == "dev"
Requires-Dist: pytest-cov>=4.0.0; extra == "dev"
Requires-Dist: black>=23.0.0; extra == "dev"
Requires-Dist: isort>=5.0.0; extra == "dev"
Requires-Dist: mypy>=1.0.0; extra == "dev"
Requires-Dist: types-requests>=2.32.0; extra == "dev"
Provides-Extra: examples
Requires-Dist: flask>=2.0.0; extra == "examples"
Requires-Dist: fastapi>=0.100.0; extra == "examples"
Requires-Dist: uvicorn>=0.20.0; extra == "examples"
Dynamic: author
Dynamic: author-email
Dynamic: classifier
Dynamic: description
Dynamic: description-content-type
Dynamic: home-page
Dynamic: keywords
Dynamic: license-file
Dynamic: project-url
Dynamic: provides-extra
Dynamic: requires-dist
Dynamic: requires-python
Dynamic: summary
